vcorg/__init__.py
vcorg/resources.py
vcorg/subsystem/__init__.py
vcorg/subsystem/sysadmin/__init__.py
vcorg/subsystem/sysadmin/domain_org/__init__.py
vcorg/subsystem/sysadmin/domain_org/resource.py
vcorg-1.0.0.dist-info/AUTHORS
vcorg-1.0.0.dist-info/METADATA
vcorg-1.0.0.dist-info/WHEEL
vcorg-1.0.0.dist-info/top_level.txt
vcorg-1.0.0.dist-info/RECORD
