Metadata-Version: 2.1
Name: vcorg
Version: 1.0.0
Summary: VCORGbackend Flask REST service
Home-page: https://bitbucket.org/vcorgb3t3/vcorg-backend
License: UNKNOWN
Platform: UNKNOWN
License-File: AUTHORS
Requires-Dist: viggocore (<2.0.0,>=1.0.0)
Requires-Dist: vclocal (>=1.0.0)
Requires-Dist: flask-cors
